akhenaten/__init__.py
akhenaten/akhenaten.py
akhenaten/definitions.py
akhenaten_py-0.2.0.dist-info/LICENSE.md
akhenaten_py-0.2.0.dist-info/METADATA
akhenaten_py-0.2.0.dist-info/WHEEL
akhenaten_py-0.2.0.dist-info/top_level.txt
akhenaten_py-0.2.0.dist-info/RECORD
