Metadata-Version: 2.1
Name: akhenaten-py
Version: 0.2.0
Summary: A python API wrapper for Akhenaten Plotly hoster
Home-page: https://github.com/AmunAnalytics/akhenaten-py
Author: Frank Boerman
Author-email: frank@amunanalytics.eu
License: MIT
Keywords: Client for Akhenaten plotly hoster
Classifier: Development Status :: 5 - Production/Stable
Classifier: Intended Audience :: Developers
Classifier: Topic :: Scientific/Engineering
Classifier: License :: OSI Approved :: MIT License
Classifier: Programming Language :: Python :: 3.10
Classifier: Programming Language :: Python :: 3.11
License-File: LICENSE.md
Requires-Dist: minio
Requires-Dist: pydantic[email]
Requires-Dist: plotly
